MANIFEST.in
README.md
requirements-django.txt
requirements-test.txt
requirements.txt
setup.py
django_data_mirror/__init__.py
django_data_mirror/admin.py
django_data_mirror/apps.py
django_data_mirror/models.py
django_data_mirror.egg-info/PKG-INFO
django_data_mirror.egg-info/SOURCES.txt
django_data_mirror.egg-info/dependency_links.txt
django_data_mirror.egg-info/not-zip-safe
django_data_mirror.egg-info/requires.txt
django_data_mirror.egg-info/top_level.txt
django_data_mirror/management/__init__.py
django_data_mirror/management/commands/__init__.py
django_data_mirror/management/commands/data_mirror_analyze.py
django_data_mirror/management/commands/data_mirror_refresh.py
django_data_mirror/tests/__init__.py
django_data_mirror/tests/commands.py
django_data_mirror/tests/manage.py
django_data_mirror/tests/models.py
django_data_mirror/tests/settings.py
django_data_mirror/tests/tests.py
django_data_mirror/tests/urls.py
django_data_mirror/tests/views.py
django_data_mirror/tests/management/__init__.py
django_data_mirror/tests/management/commands/__init__.py