Metadata-Version: 1.1
Name: django-data-mirror
Version: 0.3.0
Summary: Allows caching remote API data in local Django models.
Home-page: http://github.com/chrisspen/django-data-mirror
Author: Chris Spencer
Author-email: chrisspen@gmail.com
License: LGPLv3
Platform: UNKNOWN
Classifier: Development Status :: 4 - Beta
Classifier: Framework :: Django
Classifier: Intended Audience :: Developers
Classifier: License :: OSI Approved :: GNU Lesser General Public License v3 (LGPLv3)
Classifier: Operating System :: OS Independent
Classifier: Programming Language :: Python
